Metadata-Version: 2.1
Name: envreqs
Version: 0.1.0
Summary: An env builder for Python project
Home-page: https://github.com/santhu2210/envbuilder
Author: Shantha Kumar
Author-email: msgshanth@gmail.com
License: GNU GENERAL PUBLIC LICENSE
Classifier: Development Status :: 3 - Alpha
Classifier: Intended Audience :: Developers
Classifier: License :: OSI Approved :: GNU General Public License v3 (GPLv3)
Classifier: Operating System :: Microsoft :: Windows
Classifier: Operating System :: POSIX :: Linux
Classifier: Programming Language :: Python
Classifier: Programming Language :: Python :: 2.7
Classifier: Programming Language :: Python :: 3
Classifier: Programming Language :: Python :: 3.10
License-File: LICENSE
